toyyibpay/__init__.py
toyyibpay-0.1.0.dist-info/METADATA
toyyibpay-0.1.0.dist-info/WHEEL
toyyibpay-0.1.0.dist-info/top_level.txt
toyyibpay-0.1.0.dist-info/RECORD
